Dalmatium-1.0.0.data/data/CODE_OF_CONDUCT.md
Dalmatium-1.0.0.data/data/CONTRIBUTING.md
Dalmatium-1.0.0.data/data/LICENSE.md
Dalmatium-1.0.0.data/data/README.md
Dalmatium-1.0.0.data/data/requirements.txt
dalmatium/__config__.py
dalmatium/__init__.py
dalmatium/database.py
dalmatium/forger.py
dalmatium/py.typed
dalmatium/reader.py
dalmatium/wrapper.py
dalmatium/tests/__init__.py
dalmatium/tests/py.typed
dalmatium/tests/test_database.py
dalmatium/tests/test_forger.py
dalmatium/tests/test_wrapper.py
Dalmatium-1.0.0.dist-info/LICENSE.md
Dalmatium-1.0.0.dist-info/METADATA
Dalmatium-1.0.0.dist-info/WHEEL
Dalmatium-1.0.0.dist-info/top_level.txt
Dalmatium-1.0.0.dist-info/RECORD
