Metadata-Version: 2.1
Name: Dalmatium
Version: 1.0.0
Summary: CAD addon/plug-in to automize frameworks.
Home-page: https://github.com/IllyrionSoftware/Dalmatium
Author: IllyrionSoftware
Author-email: info@illyrion.eu
License: GNU AFFERO GENERAL PUBLIC LICENSE
Project-URL: Source Code, https://github.com/IllyrionSoftware/Dalmatium
Project-URL: Bug Tracker, https://github.com/IllyrionSoftware/Dalmatium/issues
Project-URL: Documentation, https://wiki.illyrion.eu/
Project-URL: Funding, https://buymeacoffee.com/illyrius
Requires-Python: >=3.12
License-File: LICENSE.md
Requires-Dist: build
Requires-Dist: setuptools
Requires-Dist: sqlalchemy
